aio_background/__init__.py
aio_background/aiohttp.py
aio_background/job.py
aio_background/py.typed
aio_background/run.py
aio_background-0.0.11.dist-info/LICENSE
aio_background-0.0.11.dist-info/METADATA
aio_background-0.0.11.dist-info/WHEEL
aio_background-0.0.11.dist-info/top_level.txt
aio_background-0.0.11.dist-info/RECORD
